CHANGES.txt
MANIFEST.in
README.md
requirements.txt
setup.py
organize/__init__.py
organize/csv_parser.py
organize/excel_parser.py
organize/parsers.py
organize/tsv_parser.py
organize/utils.py
organize.egg-info/PKG-INFO
organize.egg-info/SOURCES.txt
organize.egg-info/dependency_links.txt
organize.egg-info/requires.txt
organize.egg-info/top_level.txt
organize/tests/__init__.py
organize/tests/test_csv.py
organize/tests/test_excel.py
organize/tests/test_organize.py
organize/tests/test_tsv.py