Metadata-Version: 1.0
Name: organize
Version: 0.1.1
Summary: Parse real-world tabular data in a wide variety of formats.
Home-page: http://pypi.python.org/pypi/organize/
Author: Will Larson
Author-email: lethain@gmail.com
License: LICENSE.txt
Platform: UNKNOWN
